commander/__about__.py
commander/__init__.py
commander/command.py
commander/result.py
commander/runner.py
manmade2_commander-1.0.4.dist-info/METADATA
manmade2_commander-1.0.4.dist-info/WHEEL
manmade2_commander-1.0.4.dist-info/licenses/LICENSE.txt
manmade2_commander-1.0.4.dist-info/RECORD
